{
  "test_metadata": {
    "test_name": "Live Backend Non-AI Performance Report",
    "generated_at": "2025-11-16T21:47:04.436194"
  },
  "overall_summary": {
    "total_functions_measured": 1,
    "total_calls_recorded": 3
  },
  "function_performance_results": {
    "학습 로그 추가": {
      "status": "양호",
      "avg_execution_time_ms": 222.62,
      "min_execution_time_ms": 197.67,
      "max_execution_time_ms": 238.35,
      "call_count": 3,
      "type": "Database I/O Bound",
      "benchmark_ms": {
        "excellent": 200,
        "good": 400,
        "fair": 800,
        "poor": 1000
      }
    }
  }
}