{
  "test_metadata": {
    "test_name": "Live Backend Non-AI Performance Report",
    "generated_at": "2025-10-06T23:00:40.256383"
  },
  "overall_summary": {
    "total_functions_measured": 4,
    "total_calls_recorded": 13
  },
  "function_performance_results": {
    "로그인": {
      "status": "개선필요",
      "avg_execution_time_ms": 1915.3,
      "min_execution_time_ms": 1915.3,
      "max_execution_time_ms": 1915.3,
      "call_count": 1,
      "type": "Database I/O Bound",
      "benchmark_ms": {
        "excellent": 200,
        "good": 400,
        "fair": 800,
        "poor": 1000
      }
    },
    "프로필 조회": {
      "status": "양호",
      "avg_execution_time_ms": 279.08,
      "min_execution_time_ms": 253.04,
      "max_execution_time_ms": 305.11,
      "call_count": 2,
      "type": "Database I/O Bound",
      "benchmark_ms": {
        "excellent": 200,
        "good": 400,
        "fair": 800,
        "poor": 1000
      }
    },
    "오늘의 진행률 조회": {
      "status": "우수",
      "avg_execution_time_ms": 71.21,
      "min_execution_time_ms": 44.79,
      "max_execution_time_ms": 99.11,
      "call_count": 5,
      "type": "Database I/O Bound",
      "benchmark_ms": {
        "excellent": 200,
        "good": 400,
        "fair": 800,
        "poor": 1000
      }
    },
    "일일 피드백 조회": {
      "status": "우수",
      "avg_execution_time_ms": 66.07,
      "min_execution_time_ms": 37.89,
      "max_execution_time_ms": 114.64,
      "call_count": 5,
      "type": "Database I/O Bound",
      "benchmark_ms": {
        "excellent": 200,
        "good": 400,
        "fair": 800,
        "poor": 1000
      }
    }
  }
}