{
  "test_metadata": {
    "test_name": "Live Backend Non-AI Performance Report",
    "generated_at": "2025-10-15T21:56:30.137076"
  },
  "overall_summary": {
    "total_functions_measured": 5,
    "total_calls_recorded": 21
  },
  "function_performance_results": {
    "소셜 로그인 URL 생성": {
      "status": "우수",
      "avg_execution_time_ms": 9.82,
      "min_execution_time_ms": 0.45,
      "max_execution_time_ms": 41.99,
      "call_count": 8,
      "type": "Database I/O Bound",
      "benchmark_ms": {
        "excellent": 200,
        "good": 400,
        "fair": 800,
        "poor": 1000
      }
    },
    "프로필 조회": {
      "status": "양호",
      "avg_execution_time_ms": 345.38,
      "min_execution_time_ms": 202.07,
      "max_execution_time_ms": 741.74,
      "call_count": 6,
      "type": "Database I/O Bound",
      "benchmark_ms": {
        "excellent": 200,
        "good": 400,
        "fair": 800,
        "poor": 1000
      }
    },
    "일일 피드백 조회": {
      "status": "우수",
      "avg_execution_time_ms": 178.4,
      "min_execution_time_ms": 58.0,
      "max_execution_time_ms": 298.79,
      "call_count": 2,
      "type": "Database I/O Bound",
      "benchmark_ms": {
        "excellent": 200,
        "good": 400,
        "fair": 800,
        "poor": 1000
      }
    },
    "오늘의 진행률 조회": {
      "status": "우수",
      "avg_execution_time_ms": 199.24,
      "min_execution_time_ms": 99.95,
      "max_execution_time_ms": 298.53,
      "call_count": 2,
      "type": "Database I/O Bound",
      "benchmark_ms": {
        "excellent": 200,
        "good": 400,
        "fair": 800,
        "poor": 1000
      }
    },
    "로그인": {
      "status": "보통",
      "avg_execution_time_ms": 470.93,
      "min_execution_time_ms": 408.79,
      "max_execution_time_ms": 569.9,
      "call_count": 3,
      "type": "Database I/O Bound",
      "benchmark_ms": {
        "excellent": 200,
        "good": 400,
        "fair": 800,
        "poor": 1000
      }
    }
  }
}